cli_pipeline/__init__.py
cli_pipeline/cli_pipeline.py
cli_pipeline/image_to_pixels.py
cli_pipeline/templates/cluster/config/10-kubeadm.conf
cli_pipeline/templates/cluster/config/kubeadm-init.yaml
cli_pipeline/templates/cluster/yaml/admin/admin-deploy.yaml
cli_pipeline/templates/cluster/yaml/admin/admin-svc.yaml
cli_pipeline/templates/cluster/yaml/airflow/airflow-deploy.yaml.template
cli_pipeline/templates/cluster/yaml/airflow/airflow-svc.yaml.template
cli_pipeline/templates/cluster/yaml/api/api-deploy.yaml.template
cli_pipeline/templates/cluster/yaml/api/api-svc.yaml
cli_pipeline/templates/cluster/yaml/dashboard/hystrix-deploy.yaml
cli_pipeline/templates/cluster/yaml/dashboard/hystrix-svc.yaml
cli_pipeline/templates/cluster/yaml/dashboard/turbine-deploy.yaml
cli_pipeline/templates/cluster/yaml/dashboard/turbine-svc.yaml
cli_pipeline/templates/cluster/yaml/istio/crds.yaml.template
cli_pipeline/templates/cluster/yaml/istio/istio-noauth.yaml.template
cli_pipeline/templates/cluster/yaml/istio/kf-istio-resources.yaml.orig
cli_pipeline/templates/cluster/yaml/istio/pipelineai-gateway.yaml.template
cli_pipeline/templates/cluster/yaml/istio/virtualservice-airflow.yaml.template
cli_pipeline/templates/cluster/yaml/istio/virtualservice-grafana.yaml.template
cli_pipeline/templates/cluster/yaml/istio/virtualservice-mlflow.yaml.template
cli_pipeline/templates/cluster/yaml/kafka/kafka-rest-svc.yaml
cli_pipeline/templates/cluster/yaml/kafka/kafka-svc.yaml
cli_pipeline/templates/cluster/yaml/metrics/aggregated-metrics-reader.yaml
cli_pipeline/templates/cluster/yaml/metrics/auth-delegator.yaml
cli_pipeline/templates/cluster/yaml/metrics/auth-reader.yaml
cli_pipeline/templates/cluster/yaml/metrics/metrics-apiservice.yaml
cli_pipeline/templates/cluster/yaml/metrics/metrics-server-deployment.yaml
cli_pipeline/templates/cluster/yaml/metrics/metrics-server-service.yaml
cli_pipeline/templates/cluster/yaml/metrics/resource-reader.yaml
cli_pipeline-1.5.330.dist-info/METADATA
cli_pipeline-1.5.330.dist-info/WHEEL
cli_pipeline-1.5.330.dist-info/entry_points.txt
cli_pipeline-1.5.330.dist-info/top_level.txt
cli_pipeline-1.5.330.dist-info/RECORD
