Metadata-Version: 2.1
Name: cli-pipeline
Version: 1.5.330
Summary: PipelineAI CLI
Home-page: https://pipeline.ai
Author: PipelineAI
Author-email: contact@pipeline.ai
License: Apache 2.0
Keywords: machine learning artificial intelligence model training deployment optimization
Platform: UNKNOWN
Classifier: Development Status :: 5 - Production/Stable
Classifier: Intended Audience :: Developers
Classifier: Topic :: Software Development :: Build Tools
Classifier: Programming Language :: Python :: 2
Classifier: Programming Language :: Python :: 2.7
Classifier: Programming Language :: Python :: 3
Classifier: Programming Language :: Python :: 3.5
Classifier: Programming Language :: Python :: 3.6
Classifier: Programming Language :: Python :: 3.7
Requires-Python: >=2
Requires-Dist: boto3 (>=1.9.107)
Requires-Dist: fire (>=0.1.3)
Requires-Dist: jinja2 (>=2.10)
Requires-Dist: pyyaml (>=3.13)
Requires-Dist: requests (>=2.21.0)
Requires-Dist: kubernetes (>=8.0.1)
Requires-Dist: urllib3 (>=1.24.1)
Requires-Dist: gitpython (>=2.1.0)
